fiteanalytics/__init__.py
fiteanalytics/finx/__init__.py
fiteanalytics/finx/client.py
fiteanalytics/finx/client_benchmarks.py
fiteanalytics/finx/client_example.py
fiteanalytics-2.0.3.dist-info/LICENSE
fiteanalytics-2.0.3.dist-info/METADATA
fiteanalytics-2.0.3.dist-info/WHEEL
fiteanalytics-2.0.3.dist-info/top_level.txt
fiteanalytics-2.0.3.dist-info/RECORD
