Metadata-Version: 2.1
Name: fiteanalytics
Version: 2.0.3
Summary: FinX API SDK
Home-page: https://github.com/FiteAnalytics/sdk
Author: Fite Analytics LLC
Author-email: info@fiteanalytics.com
License: APGL3
Platform: UNKNOWN
Classifier: License :: OSI Approved :: GNU Affero General Public License v3
License-File: LICENSE
Requires-Dist: aiohttp
Requires-Dist: asgiref
Requires-Dist: asyncio
Requires-Dist: lru-dict
Requires-Dist: wsaccel
Requires-Dist: websocket-client
